xltektools/__init__.py
xltektools/header.py
xltektools/py.typed
xltektools/xltekcdfs/__init__.py
xltektools/xltekcdfs/arrays/__init__.py
xltektools/xltekcdfs/arrays/xltekcontentsframe.py
xltektools/xltekcdfs/components/__init__.py
xltektools/xltekcdfs/components/xltekcontentscdfscomponent.py
xltektools/xltekcdfs/components/xltekmetainformationcdfscomponent.py
xltektools/xltekcdfs/tables/__init__.py
xltektools/xltekcdfs/tables/basexltekcontentstable.py
xltektools/xltekcdfs/tables/basexltekmetainformationtable.py
xltektools/xltekcdfs/tables/basexltekvideostable.py
xltektools/xltekcdfs/tasks/__init__.py
xltektools/xltekcdfs/tasks/xltekcontentsupdatetask.py
xltektools/xltekcdfs/xltekcdfs.py
xltektools/xltekcdfs/xltekcdfsasyncschema.py
xltektools/xltekcdfs/xltekcdfsedfexporter.py
xltektools/xltekhdf5/__init__.py
xltektools/xltekhdf5/tasks/__init__.py
xltektools/xltekhdf5/tasks/xltekhdf5writertask.py
xltektools/xltekhdf5/xltekhdf5.py
xltektools/xltekhdf5/xltekhdf5_0.py
xltektools/xltekhdf5/xltekhdf5_1.py
xltektools/xltekmxbids/__init__.py
xltektools/xltekmxbids/exporters/__init__.py
xltektools/xltekmxbids/exporters/ieegxltekbidsexporter.py
xltektools/xltekmxbids/modalities/__init__.py
xltektools/xltekmxbids/modalities/ieegxltek.py
xltektools/xltekmxbids/modalities/ieegxltekcomponent.py
xltektools/xltekmxbids/sessions/__init__.py
xltektools/xltekmxbids/sessions/xltekmxbidssession.py
xltektools-0.5.2.dist-info/LICENSE
xltektools-0.5.2.dist-info/METADATA
xltektools-0.5.2.dist-info/WHEEL
xltektools-0.5.2.dist-info/entry_points.txt
xltektools-0.5.2.dist-info/RECORD
