Metadata-Version: 2.3
Name: xltektools
Version: 0.5.2
Summary: xltektools
License: MIT
Author: Anthony Fong
Author-email: fonganthonym@gmail.com
Requires-Python: >=3.10,<4.0
Classifier: Development Status :: 3 - Alpha
Classifier: License :: OSI Approved :: MIT License
Classifier: Programming Language :: Python :: 3
Classifier: Programming Language :: Python :: 3.10
Classifier: Programming Language :: Python :: 3.11
Classifier: Programming Language :: Python :: 3.12
Classifier: Programming Language :: Python :: 3.13
Requires-Dist: cdfs (>=0.3.0)
Requires-Dist: click (>=8.0.1)
Requires-Dist: hdf5objects (>=0.5.0)
Requires-Dist: mxbids (>=0.2.1)
Requires-Dist: numpy (>=1.21.2,<2.0.0)
Requires-Dist: pyEDFlib (>=0.1.36)
Project-URL: Changelog, https://github.com/fonganthonym/python-xltektools/releases
Project-URL: Documentation, https://python-xltektools.readthedocs.io
Project-URL: Homepage, https://github.com/fonganthonym/python-xltektools
Project-URL: Repository, https://github.com/fonganthonym/python-xltektools
